fscacher/__init__.py
fscacher/_version.py
fscacher/cache.py
fscacher/tests/__init__.py
fscacher/tests/test_cache.py
fscacher/tests/test_util.py
fscacher-0.4.4.dist-info/LICENSE
fscacher-0.4.4.dist-info/METADATA
fscacher-0.4.4.dist-info/WHEEL
fscacher-0.4.4.dist-info/top_level.txt
fscacher-0.4.4.dist-info/RECORD
