Metadata-Version: 2.1
Name: fscacher
Version: 0.4.4
Summary: Caching results of operations on heavy file trees
Home-page: https://github.com/con/fscacher
Author: Center for Open Neuroscience
Author-email: debian@onerussian.com
Maintainer: John T. Wodder II
Maintainer-email: fscacher@varonathe.org
License: MIT
Project-URL: Source Code, https://github.com/con/fscacher
Project-URL: Bug Tracker, https://github.com/con/fscacher/issues
Keywords: caching,file cache
Classifier: Development Status :: 4 - Beta
Classifier: Programming Language :: Python :: 3 :: Only
Classifier: Programming Language :: Python :: 3
Classifier: Programming Language :: Python :: 3.9
Classifier: Programming Language :: Python :: 3.10
Classifier: Programming Language :: Python :: 3.11
Classifier: Programming Language :: Python :: 3.12
Classifier: Programming Language :: Python :: Implementation :: CPython
Classifier: Programming Language :: Python :: Implementation :: PyPy
Classifier: License :: OSI Approved :: MIT License
Classifier: Intended Audience :: Developers
Classifier: Topic :: System :: Filesystems
Requires-Python: >=3.9
License-File: LICENSE
Requires-Dist: joblib~=1.1
Requires-Dist: platformdirs
Provides-Extra: benchmarks
Requires-Dist: asv[virtualenv]<0.6.2,~=0.6.0; extra == "benchmarks"
Provides-Extra: devel
Requires-Dist: asv[virtualenv]<0.6.2,~=0.6.0; extra == "devel"
Requires-Dist: pre-commit; extra == "devel"
Provides-Extra: all
Requires-Dist: asv[virtualenv]<0.6.2,~=0.6.0; extra == "all"
Requires-Dist: pre-commit; extra == "all"
